{
    "@context": [
        "https://www.w3.org/2018/credentials/v1"
    ],
    "id": "http://example.edu/credentials/3732",
    "type": [
        "VerifiableCredential",
        "MilitaryControlCredential"
    ],
    "issuer": "did:example:issuer12345",
    "credentialSubject": {
        "id": "did:example:abcdef1234567",
        "degree": {
            "type": "ControlPermissions",
            "name": "Drone Control Permissions"
        }
    },
    "issuanceDate": "2025-01-13T21:19:10Z",
    "hash": "18f84454a044305be4205aa2e60e3812a423f4b7c38e6cadd993afb9b313058d"
}